mltreelib/__init__.py
mltreelib/_modidx.py
mltreelib/basetree.py
mltreelib/core.py
mltreelib/data.py
mltreelib/tree.py
mltreelib/utils.py
mltreelib-0.0.2.dist-info/LICENSE
mltreelib-0.0.2.dist-info/METADATA
mltreelib-0.0.2.dist-info/WHEEL
mltreelib-0.0.2.dist-info/entry_points.txt
mltreelib-0.0.2.dist-info/top_level.txt
mltreelib-0.0.2.dist-info/RECORD
