Metadata-Version: 2.1
Name: mltreelib
Version: 0.0.2
Summary: A real tree based ML package
Home-page: https://github.com/jkapila/mltreelib
Author: Jitin Kapila
Author-email: jitin.kapila@gmail.com
License: Apache Software License 2.0
Keywords: nbdev jupyter notebook python
Platform: UNKNOWN
Classifier: Development Status :: 4 - Beta
Classifier: Intended Audience :: Developers
Classifier: Natural Language :: English
Classifier: Programming Language :: Python :: 3.7
Classifier: Programming Language :: Python :: 3.8
Classifier: Programming Language :: Python :: 3.9
Classifier: Programming Language :: Python :: 3.10
Classifier: License :: OSI Approved :: Apache Software License
Requires-Python: >=3.7
License-File: LICENSE
Requires-Dist: fastcore
Requires-Dist: pandas
Requires-Dist: numpy
Requires-Dist: scipy
Requires-Dist: statsmodels
Requires-Dist: joblib
Requires-Dist: numba
Requires-Dist: matplotlib
Provides-Extra: dev
